hostsed/__init__.py
hostsed/editor.py
hostsed-0.5.1.dist-info/METADATA
hostsed-0.5.1.dist-info/WHEEL
hostsed-0.5.1.dist-info/entry_points.txt
hostsed-0.5.1.dist-info/licenses/LICENSE
hostsed-0.5.1.dist-info/RECORD
