Metadata-Version: 2.4
Name: hostsed
Version: 0.5.1
Summary: A hosts file editing tool for command line shell.
Project-URL: Homepage, https://github.com/socrateslee/hostsed
Author: lichun
License-File: LICENSE
Classifier: Environment :: Console
Classifier: Intended Audience :: Developers
Classifier: Programming Language :: Python
Requires-Python: >=3.6
